<?xml version="1.0" encoding="utf-8"?><toc><breadcrumbs><li><a href="1A5BEC09.htm">Learn</a></li><li><a href="1A5BEC09.htm">Fluent.<wbr />Calculations.<wbr />Primitives</a></li><li><a href="8E0C130F.htm">Fluent.<wbr />Calculations.<wbr />Primitives.<wbr />Base<wbr />Types</a></li><li><a href="FAE4E8C7.htm">Option&lt;T&gt;</a></li></breadcrumbs><tocItems><li><a id="9F03FC7A" class="has-submenu" href="9F03FC7A.htm"><span data-tocFile="../toc/IDALBA.xml" class="icon toggle" onclick="ToggleExpandCollapse(this); return false;"><i class="fa fa-angle-right"> </i></span>Constructors</a><ul class="toc-menu is-hidden"> </ul></li><li><a id="975B0E14" class="has-submenu" href="975B0E14.htm"><span data-tocFile="../toc/IDBLBA.xml" class="icon toggle" onclick="ToggleExpandCollapse(this); return false;"><i class="fa fa-angle-right"> </i></span>Properties</a><ul class="toc-menu is-hidden"> </ul></li><li><a id="A73BFDBE" class="has-submenu" href="A73BFDBE.htm"><span data-tocFile="../toc/IDCLBA.xml" class="icon toggle" onclick="ToggleExpandCollapse(this); return false;"><i class="fa fa-angle-right"> </i></span>Methods</a><ul class="toc-menu is-hidden"> </ul></li><li><a id="6591BF1" class="has-submenu" href="6591BF1.htm"><span data-tocFile="../toc/IDDLBA.xml" class="icon toggle" onclick="ToggleExpandCollapse(this); return false;"><i class="fa fa-angle-right"> </i></span>Operators</a><ul class="toc-menu is-hidden"> </ul></li></tocItems></toc>